planbee/__init__.py
planbee/_version.py
planbee/models/__init__.py
planbee/models/resource.py
planbee/models/task.py
planbee/scheduler/__init__.py
planbee/scheduler/core.py
planbee/scheduler/scheduler_result.py
planbee/scheduler/task_batch_processor.py
planbee/scheduler/task_graph.py
planbee/scheduler/visualizations.py
planbee/scheduler/heuristic_solver/__init__.py
planbee/scheduler/heuristic_solver/main.py
planbee/scheduler/heuristic_solver/task_allocator.py
planbee/scheduler/heuristic_solver/window_manager.py
planbee-0.2.1.dist-info/LICENSE
planbee-0.2.1.dist-info/METADATA
planbee-0.2.1.dist-info/WHEEL
planbee-0.2.1.dist-info/top_level.txt
planbee-0.2.1.dist-info/RECORD
