Metadata-Version: 2.1
Name: planbee
Version: 0.2.1
Summary: production / job shop / resource scheduler for Python
Home-page: https://github.com/Yacobolo/PlanBee
Author: Jacob Østergaard Nielsen
Author-email: jaoe@oestergaard-as.dk
License: UNKNOWN
Platform: UNKNOWN
Classifier: Programming Language :: Python :: 3
Classifier: Operating System :: OS Independent
Classifier: License :: OSI Approved :: MIT License
Requires-Python: >=3.6
Requires-Dist: numpy
Requires-Dist: networkx
Requires-Dist: pandas
Requires-Dist: pydantic
Requires-Dist: seaborn
Requires-Dist: matplotlib
Provides-Extra: testing
Requires-Dist: pytest (>=6.0) ; extra == 'testing'
Requires-Dist: pytest-cov (>=2.0) ; extra == 'testing'
